cdek/__init__.py
cdek/client.py
cdek/constants.py
cdek/py.typed
cdek/apps/__init__.py
cdek/apps/app.py
cdek/apps/agreement/__init__.py
cdek/apps/agreement/agreement.py
cdek/apps/agreement/requests.py
cdek/apps/agreement/responses.py
cdek/apps/check/__init__.py
cdek/apps/check/check.py
cdek/apps/check/filters.py
cdek/apps/check/responses.py
cdek/apps/currency/__init__.py
cdek/apps/currency/currency.py
cdek/apps/form/__init__.py
cdek/apps/form/barcode.py
cdek/apps/form/invoice.py
cdek/apps/form/requests.py
cdek/apps/form/responses.py
cdek/apps/intake/__init__.py
cdek/apps/intake/filters.py
cdek/apps/intake/intake.py
cdek/apps/intake/requests.py
cdek/apps/intake/responses.py
cdek/apps/location/__init__.py
cdek/apps/location/filters.py
cdek/apps/location/location.py
cdek/apps/location/responses.py
cdek/apps/models/__init__.py
cdek/apps/models/contact.py
cdek/apps/models/dimensions.py
cdek/apps/models/entity_response.py
cdek/apps/models/error.py
cdek/apps/models/image.py
cdek/apps/models/intakes.py
cdek/apps/models/item.py
cdek/apps/models/location.py
cdek/apps/models/money.py
cdek/apps/models/order.py
cdek/apps/models/package.py
cdek/apps/models/payment_info.py
cdek/apps/models/phone.py
cdek/apps/models/print.py
cdek/apps/models/related_entity.py
cdek/apps/models/request.py
cdek/apps/models/seller.py
cdek/apps/models/status.py
cdek/apps/models/warning.py
cdek/apps/models/work_time.py
cdek/apps/office/__init__.py
cdek/apps/office/filters.py
cdek/apps/office/office.py
cdek/apps/office/responses.py
cdek/apps/order/__init__.py
cdek/apps/order/order.py
cdek/apps/order/requests.py
cdek/apps/order/responses.py
cdek/apps/payment/__init__.py
cdek/apps/payment/payment.py
cdek/apps/payment/responses.py
cdek/apps/tariff/__init__.py
cdek/apps/tariff/requests.py
cdek/apps/tariff/responses.py
cdek/apps/tariff/tariff.py
cdek/apps/webhook/__init__.py
cdek/apps/webhook/enums.py
cdek/apps/webhook/requests.py
cdek/apps/webhook/responses.py
cdek/apps/webhook/webhook.py
cdek-1.1.8.dist-info/licenses/LICENSE
cdek-1.1.8.dist-info/METADATA
cdek-1.1.8.dist-info/WHEEL
cdek-1.1.8.dist-info/top_level.txt
cdek-1.1.8.dist-info/RECORD
