Metadata-Version: 2.4
Name: cdek
Version: 1.1.8
Summary: CDEK Python SDK упрощает интеграцию с API СДЭК версии 2.0
Home-page: https://github.com/xxp-odoo-erp/cdek
Author: CDEK Python SDK
Author-email: Maksim Shurupov <geomer198@gmail.com>
License-Expression: Apache-2.0
Project-URL: Bug Tracker, https://github.com/xxp-odoo-erp/cdek/issues
Project-URL: Changelog, https://github.com/xxp-odoo-erp/cdek/blob/main/CHANGELOG.md
Project-URL: documentation, https://cdek.readthedocs.io/ru/latest/
Project-URL: repository, https://github.com/xxp-odoo-erp/cdek
Classifier: Development Status :: 2 - Pre-Alpha
Classifier: Intended Audience :: Developers
Classifier: Natural Language :: English
Classifier: Operating System :: OS Independent
Classifier: Programming Language :: Python :: 3.10
Classifier: Programming Language :: Python :: 3.11
Classifier: Programming Language :: Python :: 3.12
Classifier: Programming Language :: Python :: 3.13
Classifier: Programming Language :: Python :: 3.14
Classifier: Topic :: Software Development :: Libraries
Requires-Python: >=3.10
License-File: LICENSE
Requires-Dist: pydantic<3.0,>=2.6
Requires-Dist: requests>=2.28.0
Requires-Dist: rich>=10
Requires-Dist: typer<1,>=0.15
Dynamic: author
Dynamic: home-page
Dynamic: license-file
Dynamic: requires-python
